{
    "version": 2.0,
    "user_agent": "ias-label",
    "date": "2025-05-28T09:01:46.310622332+08:00",
    "last_modified": "2025-05-28T09:01:46.310622332+08:00",
    "host": "",
    "sensor": 0,
    "roi": [
        {
            "x": 0.0,
            "y": 0.0
        },
        {
            "x": 1.0,
            "y": 0.0
        },
        {
            "x": 1.0,
            "y": 0.94
        },
        {
            "x": 0.64,
            "y": 0.94
        },
        {
            "x": 0.64,
            "y": 1.0
        },
        {
            "x": 0.16666,
            "y": 1.0
        },
        {
            "x": 0.16666,
            "y": 0.94
        },
        {
            "x": 0.0,
            "y": 0.94
        }
    ],
    "objects": [
        {
            "id": 16674,
            "prob_class": {
                "value": 0,
                "conf": 0.9320743
            },
            "polygon": [
                {
                    "x": 0.0,
                    "y": 0.37925753
                },
                {
                    "x": 0.28256664,
                    "y": 0.37925753
                },
                {
                    "x": 0.28256664,
                    "y": 0.53923523
                },
                {
                    "x": 0.0,
                    "y": 0.53923523
                }
            ],
            "properties": {
                "valid": {
                    "value": -1,
                    "conf": 0.0
                }
            }
        },
        {
            "id": 16691,
            "prob_class": {
                "value": 0,
                "conf": 0.6260072
            },
            "polygon": [
                {
                    "x": 0.75295776,
                    "y": 0.37678495
                },
                {
                    "x": 0.99811774,
                    "y": 0.37678495
                },
                {
                    "x": 0.99811774,
                    "y": 0.50141406
                },
                {
                    "x": 0.75295776,
                    "y": 0.50141406
                }
            ],
            "properties": {
                "valid": {
                    "value": -1,
                    "conf": 0.0
                }
            }
        }
    ]
}