{
    "version": 2.0,
    "user_agent": "ias-label",
    "date": "2025-05-28T09:01:28.889282088+08:00",
    "last_modified": "2025-05-28T09:01:28.889282088+08:00",
    "host": "",
    "sensor": 0,
    "roi": [
        {
            "x": 0.0,
            "y": 0.0
        },
        {
            "x": 1.0,
            "y": 0.0
        },
        {
            "x": 1.0,
            "y": 0.94
        },
        {
            "x": 0.64,
            "y": 0.94
        },
        {
            "x": 0.64,
            "y": 1.0
        },
        {
            "x": 0.16666,
            "y": 1.0
        },
        {
            "x": 0.16666,
            "y": 0.94
        },
        {
            "x": 0.0,
            "y": 0.94
        }
    ],
    "objects": [
        {
            "id": 28482,
            "prob_class": {
                "value": 0,
                "conf": 0.95666116
            },
            "polygon": [
                {
                    "x": 0.56474817,
                    "y": 0.2066117
                },
                {
                    "x": 0.72159463,
                    "y": 0.2066117
                },
                {
                    "x": 0.72159463,
                    "y": 0.33771747
                },
                {
                    "x": 0.56474817,
                    "y": 0.33771747
                }
            ],
            "properties": {
                "valid": {
                    "value": -1,
                    "conf": 0.0
                }
            }
        },
        {
            "id": 28489,
            "prob_class": {
                "value": 0,
                "conf": 0.9469356
            },
            "polygon": [
                {
                    "x": 0.7168043,
                    "y": 0.21015014
                },
                {
                    "x": 0.8464447,
                    "y": 0.21015014
                },
                {
                    "x": 0.8464447,
                    "y": 0.34176013
                },
                {
                    "x": 0.7168043,
                    "y": 0.34176013
                }
            ],
            "properties": {
                "valid": {
                    "value": -1,
                    "conf": 0.0
                }
            }
        },
        {
            "id": 28485,
            "prob_class": {
                "value": 0,
                "conf": 0.94666535
            },
            "polygon": [
                {
                    "x": 0.12919873,
                    "y": 0.2027333
                },
                {
                    "x": 0.564541,
                    "y": 0.2027333
                },
                {
                    "x": 0.564541,
                    "y": 0.35199568
                },
                {
                    "x": 0.12919873,
                    "y": 0.35199568
                }
            ],
            "properties": {
                "valid": {
                    "value": -1,
                    "conf": 0.0
                }
            }
        },
        {
            "id": 28500,
            "prob_class": {
                "value": 0,
                "conf": 0.9287887
            },
            "polygon": [
                {
                    "x": 0.8406029,
                    "y": 0.23192692
                },
                {
                    "x": 0.9465545,
                    "y": 0.23192692
                },
                {
                    "x": 0.9465545,
                    "y": 0.35378376
                },
                {
                    "x": 0.8406029,
                    "y": 0.35378376
                }
            ],
            "properties": {
                "valid": {
                    "value": -1,
                    "conf": 0.0
                }
            }
        },
        {
            "id": 28468,
            "prob_class": {
                "value": 0,
                "conf": 0.6303646
            },
            "polygon": [
                {
                    "x": 0.00016851163,
                    "y": 0.28383532
                },
                {
                    "x": 0.044947147,
                    "y": 0.28383532
                },
                {
                    "x": 0.044947147,
                    "y": 0.39842966
                },
                {
                    "x": 0.00016851163,
                    "y": 0.39842966
                }
            ],
            "properties": {
                "valid": {
                    "value": -2,
                    "conf": 0.0
                }
            }
        },
        {
            "id": 28472,
            "prob_class": {
                "value": 0,
                "conf": 0.6607836
            },
            "polygon": [
                {
                    "x": 0.039534066,
                    "y": 0.25500783
                },
                {
                    "x": 0.1376768,
                    "y": 0.25500783
                },
                {
                    "x": 0.1376768,
                    "y": 0.37842527
                },
                {
                    "x": 0.039534066,
                    "y": 0.37842527
                }
            ],
            "properties": {
                "valid": {
                    "value": -2,
                    "conf": 0.0
                }
            }
        }
    ]
}