{
    "version": 2.0,
    "user_agent": "ias-label",
    "date": "2025-05-28T09:01:35.041921117+08:00",
    "last_modified": "2025-05-28T09:01:35.041921117+08:00",
    "host": "",
    "sensor": 0,
    "roi": [
        {
            "x": 0.0,
            "y": 0.0
        },
        {
            "x": 1.0,
            "y": 0.0
        },
        {
            "x": 1.0,
            "y": 0.94
        },
        {
            "x": 0.64,
            "y": 0.94
        },
        {
            "x": 0.64,
            "y": 1.0
        },
        {
            "x": 0.16666,
            "y": 1.0
        },
        {
            "x": 0.16666,
            "y": 0.94
        },
        {
            "x": 0.0,
            "y": 0.94
        }
    ],
    "objects": [
        {
            "id": 1792,
            "prob_class": {
                "value": 0,
                "conf": 0.9230305
            },
            "polygon": [
                {
                    "x": 0.27393284,
                    "y": 0.29678386
                },
                {
                    "x": 0.34867254,
                    "y": 0.29678386
                },
                {
                    "x": 0.34867254,
                    "y": 0.36571676
                },
                {
                    "x": 0.27393284,
                    "y": 0.36571676
                }
            ],
            "properties": {
                "valid": {
                    "value": -1,
                    "conf": 0.0
                }
            }
        },
        {
            "id": 1794,
            "prob_class": {
                "value": 0,
                "conf": 0.73550344
            },
            "polygon": [
                {
                    "x": 0.90158916,
                    "y": 0.37675157
                },
                {
                    "x": 1.0,
                    "y": 0.37675157
                },
                {
                    "x": 1.0,
                    "y": 0.4459908
                },
                {
                    "x": 0.90158916,
                    "y": 0.4459908
                }
            ],
            "properties": {
                "valid": {
                    "value": -2,
                    "conf": 0.0
                }
            }
        },
        {
            "id": 1782,
            "prob_class": {
                "value": 0,
                "conf": 0.9684779
            },
            "polygon": [
                {
                    "x": 0.4348223,
                    "y": 0.2764901
                },
                {
                    "x": 0.5859708,
                    "y": 0.2764901
                },
                {
                    "x": 0.5859708,
                    "y": 0.42638204
                },
                {
                    "x": 0.4348223,
                    "y": 0.42638204
                }
            ],
            "properties": {
                "valid": {
                    "value": -1,
                    "conf": 0.0
                }
            }
        }
    ]
}