{
    "version": 2.0,
    "user_agent": "ias-label",
    "date": "2025-05-28T09:02:06.709548947+08:00",
    "last_modified": "2025-05-28T09:02:06.709548947+08:00",
    "host": "",
    "sensor": 0,
    "roi": [
        {
            "x": 0.0,
            "y": 0.0
        },
        {
            "x": 1.0,
            "y": 0.0
        },
        {
            "x": 1.0,
            "y": 0.94
        },
        {
            "x": 0.64,
            "y": 0.94
        },
        {
            "x": 0.64,
            "y": 1.0
        },
        {
            "x": 0.16666,
            "y": 1.0
        },
        {
            "x": 0.16666,
            "y": 0.94
        },
        {
            "x": 0.0,
            "y": 0.94
        }
    ],
    "objects": [
        {
            "id": 14869,
            "prob_class": {
                "value": 0,
                "conf": 0.9609077
            },
            "polygon": [
                {
                    "x": 0.53699845,
                    "y": 0.34865424
                },
                {
                    "x": 0.98454946,
                    "y": 0.34865424
                },
                {
                    "x": 0.98454946,
                    "y": 0.5595674
                },
                {
                    "x": 0.53699845,
                    "y": 0.5595674
                }
            ],
            "properties": {
                "valid": {
                    "value": -1,
                    "conf": 0.0
                }
            }
        },
        {
            "id": 14907,
            "prob_class": {
                "value": 0,
                "conf": 0.9439322
            },
            "polygon": [
                {
                    "x": 0.24703456,
                    "y": 0.68512774
                },
                {
                    "x": 0.44380012,
                    "y": 0.68512774
                },
                {
                    "x": 0.44380012,
                    "y": 0.781141
                },
                {
                    "x": 0.24703456,
                    "y": 0.781141
                }
            ],
            "properties": {
                "valid": {
                    "value": -1,
                    "conf": 0.0
                }
            }
        },
        {
            "id": 14911,
            "prob_class": {
                "value": 0,
                "conf": 0.91455555
            },
            "polygon": [
                {
                    "x": 0.0056219134,
                    "y": 0.37186143
                },
                {
                    "x": 0.55079687,
                    "y": 0.37186143
                },
                {
                    "x": 0.55079687,
                    "y": 0.5324647
                },
                {
                    "x": 0.0056219134,
                    "y": 0.5324647
                }
            ],
            "properties": {
                "valid": {
                    "value": -1,
                    "conf": 0.0
                }
            }
        },
        {
            "id": 14874,
            "prob_class": {
                "value": 0,
                "conf": 0.92094755
            },
            "polygon": [
                {
                    "x": 0.5318793,
                    "y": 0.5913191
                },
                {
                    "x": 0.9691563,
                    "y": 0.5913191
                },
                {
                    "x": 0.9691563,
                    "y": 0.7219455
                },
                {
                    "x": 0.5318793,
                    "y": 0.7219455
                }
            ],
            "properties": {
                "valid": {
                    "value": -1,
                    "conf": 0.0
                }
            }
        }
    ]
}