{
    "version": 2.0,
    "user_agent": "ias-label",
    "date": "2025-05-28T09:01:31.674256016+08:00",
    "last_modified": "2025-05-28T09:01:31.674256016+08:00",
    "host": "",
    "sensor": 0,
    "roi": [
        {
            "x": 0.0,
            "y": 0.0
        },
        {
            "x": 1.0,
            "y": 0.0
        },
        {
            "x": 1.0,
            "y": 0.94
        },
        {
            "x": 0.64,
            "y": 0.94
        },
        {
            "x": 0.64,
            "y": 1.0
        },
        {
            "x": 0.16666,
            "y": 1.0
        },
        {
            "x": 0.16666,
            "y": 0.94
        },
        {
            "x": 0.0,
            "y": 0.94
        }
    ],
    "objects": [
        {
            "id": 30598,
            "prob_class": {
                "value": 0,
                "conf": 0.92192644
            },
            "polygon": [
                {
                    "x": 0.32414487,
                    "y": 0.30516794
                },
                {
                    "x": 0.41907033,
                    "y": 0.30516794
                },
                {
                    "x": 0.41907033,
                    "y": 0.3555622
                },
                {
                    "x": 0.32414487,
                    "y": 0.3555622
                }
            ],
            "properties": {
                "valid": {
                    "value": -1,
                    "conf": 0.0
                }
            }
        },
        {
            "id": 30600,
            "prob_class": {
                "value": 0,
                "conf": 0.92475176
            },
            "polygon": [
                {
                    "x": 0.4309806,
                    "y": 0.2910147
                },
                {
                    "x": 0.54104394,
                    "y": 0.2910147
                },
                {
                    "x": 0.54104394,
                    "y": 0.35372052
                },
                {
                    "x": 0.4309806,
                    "y": 0.35372052
                }
            ],
            "properties": {
                "valid": {
                    "value": -1,
                    "conf": 0.0
                }
            }
        },
        {
            "id": 30587,
            "prob_class": {
                "value": 0,
                "conf": 0.90954924
            },
            "polygon": [
                {
                    "x": 0.18761756,
                    "y": 0.2961588
                },
                {
                    "x": 0.32240945,
                    "y": 0.2961588
                },
                {
                    "x": 0.32240945,
                    "y": 0.36437595
                },
                {
                    "x": 0.18761756,
                    "y": 0.36437595
                }
            ],
            "properties": {
                "valid": {
                    "value": -1,
                    "conf": 0.0
                }
            }
        },
        {
            "id": 30590,
            "prob_class": {
                "value": 0,
                "conf": 0.66680014
            },
            "polygon": [
                {
                    "x": 0.17909075,
                    "y": 0.22068425
                },
                {
                    "x": 0.568059,
                    "y": 0.22068425
                },
                {
                    "x": 0.568059,
                    "y": 0.31305975
                },
                {
                    "x": 0.17909075,
                    "y": 0.31305975
                }
            ],
            "properties": {
                "valid": {
                    "value": -1,
                    "conf": 0.0
                }
            }
        },
        {
            "id": 30621,
            "prob_class": {
                "value": 0,
                "conf": 0.83866763
            },
            "polygon": [
                {
                    "x": 0.91327953,
                    "y": 0.3001649
                },
                {
                    "x": 0.997682,
                    "y": 0.3001649
                },
                {
                    "x": 0.997682,
                    "y": 0.37711865
                },
                {
                    "x": 0.91327953,
                    "y": 0.37711865
                }
            ],
            "properties": {
                "valid": {
                    "value": -2,
                    "conf": 0.0
                }
            }
        }
    ]
}