{
    "version": 2.0,
    "user_agent": "ias-label",
    "date": "2025-05-28T09:01:36.541459642+08:00",
    "last_modified": "2025-05-28T09:01:36.541459642+08:00",
    "host": "",
    "sensor": 0,
    "roi": [
        {
            "x": 0.0,
            "y": 0.0
        },
        {
            "x": 1.0,
            "y": 0.0
        },
        {
            "x": 1.0,
            "y": 0.94
        },
        {
            "x": 0.64,
            "y": 0.94
        },
        {
            "x": 0.64,
            "y": 1.0
        },
        {
            "x": 0.16666,
            "y": 1.0
        },
        {
            "x": 0.16666,
            "y": 0.94
        },
        {
            "x": 0.0,
            "y": 0.94
        }
    ],
    "objects": [
        {
            "id": 2792,
            "prob_class": {
                "value": 0,
                "conf": 0.9518055
            },
            "polygon": [
                {
                    "x": 0.3162195,
                    "y": 0.00022578075
                },
                {
                    "x": 0.6280193,
                    "y": 0.00022578075
                },
                {
                    "x": 0.6280193,
                    "y": 0.17305495
                },
                {
                    "x": 0.3162195,
                    "y": 0.17305495
                }
            ],
            "properties": {
                "valid": {
                    "value": -1,
                    "conf": 0.0
                }
            }
        },
        {
            "id": 2788,
            "prob_class": {
                "value": 0,
                "conf": 0.95443755
            },
            "polygon": [
                {
                    "x": 0.61637914,
                    "y": 0.00008306746
                },
                {
                    "x": 0.779792,
                    "y": 0.00008306746
                },
                {
                    "x": 0.779792,
                    "y": 0.18129084
                },
                {
                    "x": 0.61637914,
                    "y": 0.18129084
                }
            ],
            "properties": {
                "valid": {
                    "value": -1,
                    "conf": 0.0
                }
            }
        },
        {
            "id": 2822,
            "prob_class": {
                "value": 0,
                "conf": 0.9194039
            },
            "polygon": [
                {
                    "x": 0.00003962416,
                    "y": 0.18982553
                },
                {
                    "x": 0.09152296,
                    "y": 0.18982553
                },
                {
                    "x": 0.09152296,
                    "y": 0.34655267
                },
                {
                    "x": 0.00003962416,
                    "y": 0.34655267
                }
            ],
            "properties": {
                "valid": {
                    "value": -2,
                    "conf": 0.0
                }
            }
        },
        {
            "id": 2823,
            "prob_class": {
                "value": 0,
                "conf": 0.9476315
            },
            "polygon": [
                {
                    "x": 0.78229505,
                    "y": 0.035423055
                },
                {
                    "x": 0.9404345,
                    "y": 0.035423055
                },
                {
                    "x": 0.9404345,
                    "y": 0.26754162
                },
                {
                    "x": 0.78229505,
                    "y": 0.26754162
                }
            ],
            "properties": {
                "valid": {
                    "value": -1,
                    "conf": 0.0
                }
            }
        }
    ]
}