{
    "version": 2.0,
    "user_agent": "ias-label",
    "date": "2025-05-28T09:01:32.167993407+08:00",
    "last_modified": "2025-05-28T09:01:32.167993407+08:00",
    "host": "",
    "sensor": 0,
    "roi": [
        {
            "x": 0.0,
            "y": 0.0
        },
        {
            "x": 1.0,
            "y": 0.0
        },
        {
            "x": 1.0,
            "y": 0.94
        },
        {
            "x": 0.64,
            "y": 0.94
        },
        {
            "x": 0.64,
            "y": 1.0
        },
        {
            "x": 0.16666,
            "y": 1.0
        },
        {
            "x": 0.16666,
            "y": 0.94
        },
        {
            "x": 0.0,
            "y": 0.94
        }
    ],
    "objects": [
        {
            "id": 31265,
            "prob_class": {
                "value": 0,
                "conf": 0.9341758
            },
            "polygon": [
                {
                    "x": 0.34843552,
                    "y": 0.2574811
                },
                {
                    "x": 0.6903656,
                    "y": 0.2574811
                },
                {
                    "x": 0.6903656,
                    "y": 0.37047663
                },
                {
                    "x": 0.34843552,
                    "y": 0.37047663
                }
            ],
            "properties": {
                "valid": {
                    "value": -1,
                    "conf": 0.0
                }
            }
        },
        {
            "id": 31280,
            "prob_class": {
                "value": 0,
                "conf": 0.95841414
            },
            "polygon": [
                {
                    "x": 0.67761004,
                    "y": 0.21498184
                },
                {
                    "x": 0.9600723,
                    "y": 0.21498184
                },
                {
                    "x": 0.9600723,
                    "y": 0.37994277
                },
                {
                    "x": 0.67761004,
                    "y": 0.37994277
                }
            ],
            "properties": {
                "valid": {
                    "value": -1,
                    "conf": 0.0
                }
            }
        }
    ]
}